st_link_analysis_sansa/__init__.py
st_link_analysis_sansa/component/__init__.py
st_link_analysis_sansa/component/component.py
st_link_analysis_sansa/component/events.py
st_link_analysis_sansa/component/icons.py
st_link_analysis_sansa/component/layouts.py
st_link_analysis_sansa/component/styles.py
st_link_analysis_sansa/frontend/build/32b01d6a21d9433a251c.ttf
st_link_analysis_sansa/frontend/build/apache-arrow.6795ba5a5a6f1b4c9100.bundle.js
st_link_analysis_sansa/frontend/build/cytoscape.f552fc7815336b8b176e.bundle.js
st_link_analysis_sansa/frontend/build/cytoscape.f552fc7815336b8b176e.bundle.js.LICENSE.txt
st_link_analysis_sansa/frontend/build/index.92aa009d0a34c59ace45.bundle.js
st_link_analysis_sansa/frontend/build/index.html
st_link_analysis_sansa/frontend/build/runtime.f45e30ba52052b8fb0c1.bundle.js
st_link_analysis_sansa/frontend/build/streamlit-component-lib.a45f9d47188ad6ed597f.bundle.js
st_link_analysis_sansa/frontend/build/vendors.19de8d7b23d1a57d52fd.bundle.js
st_link_analysis_sansa/frontend/build/vendors.19de8d7b23d1a57d52fd.bundle.js.LICENSE.txt
st_link_analysis_sansa/frontend/build/icons/account_balance.svg
st_link_analysis_sansa/frontend/build/icons/alternate_email.svg
st_link_analysis_sansa/frontend/build/icons/analytics.svg
st_link_analysis_sansa/frontend/build/icons/assured_workload.svg
st_link_analysis_sansa/frontend/build/icons/badge.svg
st_link_analysis_sansa/frontend/build/icons/business.svg
st_link_analysis_sansa/frontend/build/icons/campaign.svg
st_link_analysis_sansa/frontend/build/icons/cell_tower.svg
st_link_analysis_sansa/frontend/build/icons/chat.svg
st_link_analysis_sansa/frontend/build/icons/cloud.svg
st_link_analysis_sansa/frontend/build/icons/credit_card.svg
st_link_analysis_sansa/frontend/build/icons/description.svg
st_link_analysis_sansa/frontend/build/icons/directions_car.svg
st_link_analysis_sansa/frontend/build/icons/dns.svg
st_link_analysis_sansa/frontend/build/icons/email.svg
st_link_analysis_sansa-0.3.4.dist-info/METADATA
st_link_analysis_sansa-0.3.4.dist-info/WHEEL
st_link_analysis_sansa-0.3.4.dist-info/licenses/LICENSE
st_link_analysis_sansa-0.3.4.dist-info/RECORD
