Metadata-Version: 2.4
Name: st_link_analysis_sansa
Version: 0.3.4
Summary: A streamlit custom component for visualizing and interacting with graphs
Project-URL: Homepage, https://github.com/sansagara/st-link-analysis
Project-URL: Issues, https://github.com/sansagara/st-link-analysis/issues
Author: sansagara
License-Expression: MIT
License-File: LICENSE
Keywords: cytoscape,graph,link analysis,streamlit
Classifier: License :: OSI Approved :: MIT License
Classifier: Operating System :: OS Independent
Classifier: Programming Language :: Python :: 3
Requires-Python: >=3.8
Requires-Dist: streamlit>=0.63
